insh/__init__.py
insh/command_line.py
insh/config.py
insh/shell.py
insh-2.0.data/data/LICENSE
insh-2.0.dist-info/LICENSE
insh-2.0.dist-info/METADATA
insh-2.0.dist-info/WHEEL
insh-2.0.dist-info/entry_points.txt
insh-2.0.dist-info/top_level.txt
insh-2.0.dist-info/RECORD
