Metadata-Version: 2.1
Name: insh
Version: 2.0
Summary: A Python package that insults you when you encounter an error
Home-page: https://github.com/TheSpeedX/insh
Download-URL: https://github.com/TheSpeedX/insh/archive/master.zip
Author: TheSpeedX
License: MIT
Keywords: shell,funny,gpt,python
Classifier: Development Status :: 4 - Beta
Classifier: Intended Audience :: Developers
Classifier: Topic :: Software Development :: Libraries :: Python Modules
Classifier: License :: OSI Approved :: MIT License
Classifier: Programming Language :: Python :: 3
Classifier: Operating System :: OS Independent
Classifier: Environment :: Console
License-File: LICENSE
Requires-Dist: openai <2,>=1.13.3
